llama_index/packs/panel_chatbot/__init__.py
llama_index/packs/panel_chatbot/app.py
llama_index/packs/panel_chatbot/base.py
llama_index/packs/panel_chatbot/llama_by_sophia_yang.png
llama_index/packs/panel_chatbot/panel_chatbot.png
llama_index_packs_panel_chatbot-0.4.1.dist-info/METADATA
llama_index_packs_panel_chatbot-0.4.1.dist-info/WHEEL
llama_index_packs_panel_chatbot-0.4.1.dist-info/licenses/LICENSE
llama_index_packs_panel_chatbot-0.4.1.dist-info/RECORD
