Metadata-Version: 2.4
Name: llama-index-packs-panel-chatbot
Version: 0.4.1
Summary: llama-index packs panel_chatbot integration
Author-email: Your Name <you@example.com>
Maintainer: MarcSkovMadsen
License-Expression: MIT
License-File: LICENSE
Keywords: chatbot,github,index,openai,panel
Requires-Python: <4.0,>=3.9
Requires-Dist: llama-index-core<0.15,>=0.13.0
Requires-Dist: llama-index-readers-github<0.9,>=0.8.0
Requires-Dist: nest-asyncio<2,>=1.6.0
Requires-Dist: panel<2,>=1.3.8
